cdktf_cdk8s/__init__.py
cdktf_cdk8s/py.typed
cdktf_cdk8s/_jsii/__init__.py
cdktf_cdk8s/_jsii/cdktf-cdk8s@0.11.27.jsii.tgz
cdktf_cdk8s-0.11.27.dist-info/LICENSE
cdktf_cdk8s-0.11.27.dist-info/METADATA
cdktf_cdk8s-0.11.27.dist-info/WHEEL
cdktf_cdk8s-0.11.27.dist-info/top_level.txt
cdktf_cdk8s-0.11.27.dist-info/RECORD
