Metadata-Version: 2.1
Name: cdktf-cdk8s
Version: 0.11.27
Summary: A compatibility layer for using cdk8s constructs within Terraform CDK.
Home-page: https://github.com/cdktf/cdktf-cdk8s.git
Author: HashiCorp
License: MPL-2.0
Project-URL: Source, https://github.com/cdktf/cdktf-cdk8s.git
Classifier: Intended Audience :: Developers
Classifier: Operating System :: OS Independent
Classifier: Programming Language :: JavaScript
Classifier: Programming Language :: Python :: 3 :: Only
Classifier: Programming Language :: Python :: 3.9
Classifier: Programming Language :: Python :: 3.10
Classifier: Programming Language :: Python :: 3.11
Classifier: Typing :: Typed
Classifier: Development Status :: 4 - Beta
Classifier: License :: OSI Approved
Requires-Python: ~=3.9
License-File: LICENSE
Requires-Dist: cdk8s >=2.8.0
Requires-Dist: cdktf-cdktf-provider-kubernetes >=12.0.0
Requires-Dist: cdktf >=0.21.0
Requires-Dist: constructs <11.0.0,>=10.4.2
Requires-Dist: jsii <2.0.0,>=1.120.0
Requires-Dist: publication >=0.0.3
Requires-Dist: typeguard ==2.13.3
